{
  "project_info": {
    "project_number": "425344741206",
    "firebase_url": "https://oldiary-default-rtdb.firebaseio.com",
    "project_id": "oldiary",
    "storage_bucket": "oldiary.appspot.com"
  },
  "client": [
    {
      "client_info": {
        "mobilesdk_app_id": "1:425344741206:android:4cd51a504f18b10a85f0f7",
        "android_client_info": {
          "package_name": "com.example.oldiary"
        }
      },
      "oauth_client": [
        {
          "client_id": "425344741206-2353ko1auhs3cp22r59vsesherhnb879.apps.googleusercontent.com",
          "client_type": 1,
          "android_info": {
            "package_name": "com.example.oldiary",
            "certificate_hash": "9ca3f9b884b20b74bcc0755637edeb55c3e0c728"
          }
        },
        {
          "client_id": "425344741206-bk49svnek05gf4pamvg84n02cgasqq99.apps.googleusercontent.com",
          "client_type": 1,
          "android_info": {
            "package_name": "com.example.oldiary",
            "certificate_hash": "a0b54b915f28eafde47730a7eaf4eb28e4410710"
          }
        },
        {
          "client_id": "425344741206-m3b94gj5m5nb0tt34tpvjh5kvtj0bfih.apps.googleusercontent.com",
          "client_type": 1,
          "android_info": {
            "package_name": "com.example.oldiary",
            "certificate_hash": "4087cf5308b242fa45887bbefa655b72d816ef4f"
          }
        },
        {
          "client_id": "425344741206-olvqr26vromsc9am6mk85clrvrv2c4c4.apps.googleusercontent.com",
          "client_type": 1,
          "android_info": {
            "package_name": "com.example.oldiary",
            "certificate_hash": "37ca0836c84e97962c41974a122cb841d7f407f7"
          }
        },
        {
          "client_id": "425344741206-rfb7otkc56in2dtum4hnss78fss0nse7.apps.googleusercontent.com",
          "client_type": 1,
          "android_info": {
            "package_name": "com.example.oldiary",
            "certificate_hash": "5273fd88df6516503eed155c5bed2e015ba4221b"
          }
        },
        {
          "client_id": "425344741206-61s9vuicku45qnp3uno6qu175oaknuvk.apps.googleusercontent.com",
          "client_type": 3
        }
      ],
      "api_key": [
        {
          "current_key": "AIzaSyDYFEZqI64q0kd5z8OGbvzIh3Ujyn8rsYo"
        }
      ],
      "services": {
        "appinvite_service": {
          "other_platform_oauth_client": [
            {
              "client_id": "425344741206-61s9vuicku45qnp3uno6qu175oaknuvk.apps.googleusercontent.com",
              "client_type": 3
            }
          ]
        }
      }
    }
  ],
  "configuration_version": "1"
}